odoo/addons/l10n_ro_account_report_invoice/README.rst
odoo/addons/l10n_ro_account_report_invoice/__init__.py
odoo/addons/l10n_ro_account_report_invoice/__manifest__.py
odoo/addons/l10n_ro_account_report_invoice/i18n/l10n_ro_account_report_invoice.pot
odoo/addons/l10n_ro_account_report_invoice/i18n/ro.po
odoo/addons/l10n_ro_account_report_invoice/models/__init__.py
odoo/addons/l10n_ro_account_report_invoice/models/account_move.py
odoo/addons/l10n_ro_account_report_invoice/models/res_company.py
odoo/addons/l10n_ro_account_report_invoice/models/res_config_settings.py
odoo/addons/l10n_ro_account_report_invoice/models/sale_order.py
odoo/addons/l10n_ro_account_report_invoice/readme/CONTRIBUTORS.md
odoo/addons/l10n_ro_account_report_invoice/readme/DESCRIPTION.md
odoo/addons/l10n_ro_account_report_invoice/readme/INSTALL.md
odoo/addons/l10n_ro_account_report_invoice/static/description/icon.png
odoo/addons/l10n_ro_account_report_invoice/static/description/index.html
odoo/addons/l10n_ro_account_report_invoice/views/account_invoice_view.xml
odoo/addons/l10n_ro_account_report_invoice/views/invoice_report.xml
odoo/addons/l10n_ro_account_report_invoice/views/res_config_settings_view.xml
odoo_addon_l10n_ro_account_report_invoice-18.0.0.2.0.dist-info/METADATA
odoo_addon_l10n_ro_account_report_invoice-18.0.0.2.0.dist-info/WHEEL
odoo_addon_l10n_ro_account_report_invoice-18.0.0.2.0.dist-info/top_level.txt
odoo_addon_l10n_ro_account_report_invoice-18.0.0.2.0.dist-info/RECORD
